csv_jsonl.py
test/__init__.py
test/test_dict_writer.py
test/test_list_writer.py
csv_jsonl-0.1.6.dist-info/LICENSE.txt
csv_jsonl-0.1.6.dist-info/METADATA
csv_jsonl-0.1.6.dist-info/WHEEL
csv_jsonl-0.1.6.dist-info/top_level.txt
csv_jsonl-0.1.6.dist-info/zip-safe
csv_jsonl-0.1.6.dist-info/RECORD
