Metadata-Version: 2.1
Name: csv-jsonl
Version: 0.1.6
Summary: Leverage the built-in python csv module to write files in jsonl format
Home-page: https://gitlab.com/doug.shawhan/csv-jsonl
Author: Doug Shawhan
Author-email: doug.shawhan@gmail.com
License: UNKNOWN
Project-URL: Bug Tracker, https://gitlab.com/doug.shawhan/csv-jsonl/issues
Project-URL: Source Code, https://gitlab.com/doug.shawhan/csv-jsonl/tree/main
Project-URL: Development Version, https://gitlab.com/doug.shawhan/csv-jsonl/tree/dev
Project-URL: Documentation, https://csv-jsonl.readthedocs.io
Keywords: python,jsonl,jsonlines,csv,bigquery
Platform: any
Classifier: Programming Language :: Python :: 3
Classifier: Programming Language :: Python :: 3.7
Classifier: Programming Language :: Python :: 3.8
Classifier: Programming Language :: Python :: 3.9
Classifier: Programming Language :: Python :: 3.10
Classifier: Intended Audience :: Developers
Classifier: Operating System :: OS Independent
Classifier: Topic :: Software Development :: Libraries :: Python Modules
Requires-Python: >=3.7
License-File: LICENSE.txt
